aiq/meta/pypi.md
aiq/plugins/ragaai/__init__.py
aiq/plugins/ragaai/ragaai_catalyst_exporter.py
aiq/plugins/ragaai/register.py
aiq/plugins/ragaai/mixin/__init__.py
aiq/plugins/ragaai/mixin/ragaai_catalyst_mixin.py
aiqtoolkit_ragaai-1.2.0a20250806.dist-info/METADATA
aiqtoolkit_ragaai-1.2.0a20250806.dist-info/WHEEL
aiqtoolkit_ragaai-1.2.0a20250806.dist-info/entry_points.txt
aiqtoolkit_ragaai-1.2.0a20250806.dist-info/top_level.txt
aiqtoolkit_ragaai-1.2.0a20250806.dist-info/RECORD
