Metadata-Version: 2.4
Name: aiqtoolkit-ragaai
Version: 1.2.0a20250806
Summary: Subpackage for RagaAI Catalyst integration in AIQtoolkit
Keywords: ai,observability,ragaai catalyst
Classifier: Programming Language :: Python
Requires-Python: <3.13,>=3.11
Requires-Dist: aiqtoolkit[opentelemetry]==v1.2.0a20250806
Requires-Dist: ragaai-catalyst<2.3,>=2.2.0
